ticktick_mcp/__init__.py
ticktick_mcp/authenticate.py
ticktick_mcp/cli.py
ticktick_mcp/src/__init__.py
ticktick_mcp/src/auth.py
ticktick_mcp/src/server.py
ticktick_mcp/src/ticktick_client.py
mseep_ticktick_mcp-0.1.0.dist-info/METADATA
mseep_ticktick_mcp-0.1.0.dist-info/WHEEL
mseep_ticktick_mcp-0.1.0.dist-info/entry_points.txt
mseep_ticktick_mcp-0.1.0.dist-info/top_level.txt
mseep_ticktick_mcp-0.1.0.dist-info/RECORD
