Metadata-Version: 2.4
Name: mseep-ticktick-mcp
Version: 0.1.0
Summary: Model Context Protocol (MCP) server for TickTick task management
Home-page: https://github.com/parkjs814/ticktick-mcp
Author: mseep
Author-email: parkjs814@gmail.com
Maintainer: mseep
Maintainer-email: support@skydeck.ai
Classifier: Development Status :: 3 - Alpha
Classifier: Intended Audience :: Developers
Classifier: License :: OSI Approved :: MIT License
Classifier: Programming Language :: Python :: 3
Classifier: Programming Language :: Python :: 3.10
Classifier: Programming Language :: Python :: 3.11
Classifier: Programming Language :: Python :: 3.12
Requires-Python: >=3.10
Requires-Dist: mcp[cli]<2.0.0,>=1.2.0
Requires-Dist: python-dotenv<2.0.0,>=1.0.0
Requires-Dist: requests<3.0.0,>=2.30.0
Dynamic: author
Dynamic: author-email
Dynamic: classifier
Dynamic: description
Dynamic: description-content-type
Dynamic: home-page
Dynamic: maintainer
Dynamic: maintainer-email
Dynamic: requires-dist
Dynamic: requires-python
Dynamic: summary
